amapy_plugin_posix/__init__.py
amapy_plugin_posix/posix_blob.py
amapy_plugin_posix/posix_mixin.py
amapy_plugin_posix/posix_storage.py
amapy_plugin_posix/posix_url.py
amapy_plugin_posix/tests/__init__.py
amapy_plugin_posix/tests/test_posix_storage.py
amapy_plugin_posix/transporter/__init__.py
amapy_plugin_posix/transporter/async_posix_transporter.py
amapy_plugin_posix/transporter/async_shutil.py
amapy_plugin_posix/transporter/posix_transport_resource.py
amapy_plugin_posix/transporter/tests/__init__.py
amapy_plugin_posix/transporter/tests/test_async_posix_transporter.py
amapy_plugin_posix-1.0.1.dist-info/METADATA
amapy_plugin_posix-1.0.1.dist-info/WHEEL
amapy_plugin_posix-1.0.1.dist-info/top_level.txt
amapy_plugin_posix-1.0.1.dist-info/RECORD
