Metadata-Version: 2.1
Name: amapy-plugin-posix
Version: 1.0.1
Summary: The POSIX plugin for the ama project.
Author-email: Swarup Mahanti <swarup.mahanti@roche.com>
Maintainer-email: Swarup Mahanti <swarup.mahanti@roche.com>
License: Copyright (c) 2024 Roche Diagnostics Computation Science & Informatics
Requires-Python: <3.11,>=3.10
Requires-Dist: amapy-contents==1.*
Requires-Dist: amapy-pluggy==1.*
Requires-Dist: amapy-utils==1.*
